web_image_downloader/__init__.py
web_image_downloader/downloader.py
web_image_downloader-1.0.dist-info/METADATA
web_image_downloader-1.0.dist-info/WHEEL
web_image_downloader-1.0.dist-info/dependency_links.txt
web_image_downloader-1.0.dist-info/entry_points.txt
web_image_downloader-1.0.dist-info/top_level.txt
web_image_downloader-1.0.dist-info/RECORD
