Metadata-Version: 2.1
Name: web-image-downloader
Version: 1.0
Summary: A package to download images from the web using web_assets_downloader.
Home-page: https://github.com/arif-x/web-image-downloader
Author: Ariffudin
Author-email: sudo.ariffudin@gmail.com
Project-URL: Source, https://github.com/arif-x/web-image-downloader
Project-URL: Source Code, https://github.com/arif-x/web-image-downloader
Classifier: Programming Language :: Python :: 3
Classifier: License :: OSI Approved :: MIT License
Classifier: Operating System :: OS Independent
Requires-Python: >=3.6
Requires-Dist: web-assets-downloader
